{
	"format_version": "1.8.0",
	"animations": {
		"axedefenseidle": {
			"loop": true,
			"animation_length": 2,
			"hold_last_frame": true,
			"bones": {
				"head": {
					"position": {
						"0.0": {
							"vector": [0, 0, 1]
						},
						"1.0": {
							"vector": [0, 0, -1]
						},
						"2.0": {
							"vector": [0, 0, 1]
						}
					}
				},
				"torso": {
					"rotation": {
						"0.0": {
							"vector": [10, 20, 0]
						},
						"1.0": {
							"vector": [15, 20, 0]
						},
						"2.0": {
							"vector": [10, 20, 0]
						}
					},
					"position": {
						"0.0": {
							"vector": [0, 0, 1]
						},
						"1.0": {
							"vector": [0, 0, -1]
						},
						"2.0": {
							"vector": [0, 0, 1]
						}
					}
				},
				"rightArm": {
					"rotation": {
						"0.0": {
							"vector": [-34.89963, -9.28945, 39.15093]
						},
						"2.0": {
							"vector": [-34.89963, -9.28945, 39.15093]
						}
					},
					"position": {
						"0.0": {
							"vector": [1, -1.2, 3]
						},
						"1.0": {
							"vector": [1, -1.2, 1]
						},
						"2.0": {
							"vector": [1, -1.2, 3]
						}
					}
				},
				"leftArm": {
					"rotation": {
						"0.0": {
							"vector": [26.94093, 5.73576, -11.12501]
						},
						"2.0": {
							"vector": [26.94093, 5.73576, -11.12501]
						}
					},
					"position": {
						"0.0": {
							"vector": [0, 0, -1]
						},
						"1.0": {
							"vector": [0, -0.5, -2]
						},
						"2.0": {
							"vector": [0, 0, -1]
						}
					}
				},
				"rightLeg": {
					"rotation": {
						"0.0": {
							"vector": [22.5, 0, 0]
						},
						"2.0": {
							"vector": [22.5, 0, 0]
						}
					},
					"position": {
						"0.0": {
							"vector": [0, 0, 3.4]
						},
						"1.0": {
							"vector": [0, 0.2, 3.4]
						},
						"2.0": {
							"vector": [0, 0, 3.4]
						}
					}
				},
				"leftLeg": {
					"rotation": {
						"0.0": {
							"vector": [0, 0, 0]
						},
						"2.0": {
							"vector": [0, 0, 0]
						}
					},
					"position": {
						"0.0": {
							"vector": [0, 0, 0]
						},
						"2.0": {
							"vector": [0, 0, 0]
						}
					}
				}
			}
		}
	},
	"geckolib_format_version": 2
}